neurion_sanctum/__init__.py
neurion_sanctum/aws/__init__.py
neurion_sanctum/aws/docker.py
neurion_sanctum/aws/ec2.py
neurion_sanctum/aws/enclave.py
neurion_sanctum/blockchain/__init__.py
neurion_sanctum/blockchain/client.py
neurion_sanctum/blockchain/message.py
neurion_sanctum/blockchain/query.py
neurion_sanctum/blockchain/wallet.py
neurion_sanctum/crypt/__init__.py
neurion_sanctum/main.py
neurion_sanctum/processor/__init__.py
neurion_sanctum/processor/processor.py
neurion_sanctum/setting/__init__.py
neurion_sanctum/store/__init__.py
neurion_sanctum/store/huggingface.py
neurion_sanctum/task/__init__.py
neurion_sanctum/task/task.py
neurion_sanctum/utils/__init__.py
neurion_sanctum-0.4.0.dist-info/METADATA
neurion_sanctum-0.4.0.dist-info/WHEEL
neurion_sanctum-0.4.0.dist-info/RECORD
