Metadata-Version: 2.3
Name: neurion-sanctum
Version: 0.4.0
Summary: 
Author: Ryon
Author-email: zhangruiyang36@gmail.com
Requires-Python: >=3.12,<4.0
Classifier: Programming Language :: Python :: 3
Classifier: Programming Language :: Python :: 3.12
Classifier: Programming Language :: Python :: 3.13
Requires-Dist: boto3 (>=1.37.4,<2.0.0)
Requires-Dist: cryptography (>=44.0.1,<45.0.0)
Requires-Dist: fastapi (>=0.115.8,<0.116.0)
Requires-Dist: huggingface-hub (>=0.29.1,<0.30.0)
Requires-Dist: neurionpy (==0.18.0)
Requires-Dist: paramiko (>=3.5.1,<4.0.0)
Requires-Dist: pydantic (>=2.10.6,<3.0.0)
Requires-Dist: requests (>=2.32.3,<3.0.0)
Requires-Dist: ruamel-yaml (>=0.18.10,<0.19.0)
Requires-Dist: tomli (>=2.2.1,<3.0.0)
Requires-Dist: uvicorn (>=0.34.0,<0.35.0)
